Workbook

Sheet README
B2: Inventory & Demand Forecasting Analytics for E-commerce Fulfillment
B3: Excel + SQL demand forecasting model, ABC analysis, and reorder-point / safety-stock calculator
B5: Sheet | C5: Contents
B6: SKU_Master | C6: SKU catalog: category, cost, price, supplier lead time, MOQ (input data).
B7: Demand_Stats | C7: 90-day avg & std-dev daily demand per SKU, sourced from SQL (02_demand_stats.sql).
B8: ABC_Analysis | C8: Revenue-based Pareto classification (A/B/C) — LIVE Excel formulas (RANK, running SUM, IF).
B9: Reorder_Point_Calc | C9: Safety stock & reorder point per SKU — LIVE formulas, service level driven by ABC class.
B10: Fill_Rate_Impact | C10: Baseline vs simulated fill rate after applying the new reorder policy (before/after).
B11: Forecast_Model | C11: ML demand-forecast model comparison (WMAPE) and next-week forecast per SKU.
B12: Reorder_Alerts | C12: Automated, prioritized reorder alert list (urgency-ranked) — the AI-automation output.
B15: Color legend:
B16: Blue text = hardcoded input / external source
B17: Black text = live Excel formula

Sheet SKU_Master
A1: SKU ID | B1: SKU Name | C1: Category | D1: Unit Cost (₹) | E1: Unit Price (₹) | F1: Lead Time (days) | G1: MOQ (units) | H1: Fulfillment Centers
A2: SKU0001 | B2: Mobiles Item 001 | C2: Mobiles & Accessories | D2: 15506.63 | E2: 19574.72 | F2: 5 | G2: 50 | H2: FC03|FC05
A3: SKU0002 | B3: Mobiles Item 002 | C3: Mobiles & Accessories | D3: 14946.65 | E3: 19865.33 | F3: 4 | G3: 20 | H3: FC05|FC02|FC03|FC04
A4: SKU0003 | B4: Mobiles Item 003 | C4: Mobiles & Accessories | D4: 10648.75 | E4: 14309.59 | F4: 5 | G4: 50 | H4: FC02|FC05|FC01|FC03
A5: SKU0004 | B5: Mobiles Item 004 | C5: Mobiles & Accessories | D5: 4512.26 | E5: 5670.52 | F5: 3 | G5: 20 | H5: FC04|FC03|FC02
A6: SKU0005 | B6: Mobiles Item 005 | C6: Mobiles & Accessories | D6: 7873.78 | E6: 9890.4 | F6: 2 | G6: 25 | H6: FC01|FC04|FC03
A7: SKU0006 | B7: Mobiles Item 006 | C7: Mobiles & Accessories | D7: 17325.19 | E7: 20984.11 | F7: 7 | G7: 10 | H7: FC05|FC03|FC04|FC02
A8: SKU0007 | B8: Mobiles Item 007 | C8: Mobiles & Accessories | D8: 4272.05 | E8: 5797 | F8: 5 | G8: 25 | H8: FC01|FC03|FC04
A9: SKU0008 | B9: Mobiles Item 008 | C9: Mobiles & Accessories | D9: 3268.58 | E9: 4354.27 | F9: 4 | G9: 25 | H9: FC01|FC03|FC04
A10: SKU0009 | B10: Mobiles Item 009 | C10: Mobiles & Accessories | D10: 11174.55 | E10: 14420.53 | F10: 4 | G10: 100 | H10: FC02|FC03
A11: SKU0010 | B11: Mobiles Item 010 | C11: Mobiles & Accessories | D11: 4917.1 | E11: 6613.78 | F11: 3 | G11: 50 | H11: FC01|FC03|FC05
A12: SKU0011 | B12: Mobiles Item 011 | C12: Mobiles & Accessories | D12: 9034.35 | E12: 10752.69 | F12: 2 | G12: 25 | H12: FC04|FC05
A13: SKU0012 | B13: Mobiles Item 012 | C13: Mobiles & Accessories | D13: 3896.4 | E13: 4869.68 | F13: 5 | G13: 50 | H13: FC05|FC02|FC01
... A151: SKU0150 | B151: Grocery Item 020 | C151: Grocery & Essentials | D151: 105.86 | E151: 161.96 | F151: 3 | G151: 50 | H151: FC03|FC02|FC01|FC05

Sheet Demand_Stats
A1: SKU ID | B1: Days Observed | C1: Avg Daily Demand | D1: Std Dev Daily Demand | F1: Source: SQL view v_sku_demand_stats_90d (02_demand_stats.sql), trailing 90 days of daily_sales fact table.
A2: SKU0001 | B2: 90 | C2: 52.63 | D2: 24.39
A3: SKU0002 | B3: 90 | C3: 33.32 | D3: 16.7
A4: SKU0003 | B4: 90 | C4: 53.84 | D4: 27
A5: SKU0004 | B5: 90 | C5: 14.69 | D5: 8.05
A6: SKU0005 | B6: 90 | C6: 21.77 | D6: 10.92
A7: SKU0006 | B7: 90 | C7: 27.13 | D7: 14.8
A8: SKU0007 | B8: 90 | C8: 49.72 | D8: 23.57
A9: SKU0008 | B9: 90 | C9: 44.82 | D9: 22.42
A10: SKU0009 | B10: 90 | C10: 13.59 | D10: 7.63
A11: SKU0010 | B11: 90 | C11: 26.71 | D11: 13.2
A12: SKU0011 | B12: 90 | C12: 20.89 | D12: 11.88
A13: SKU0012 | B13: 90 | C13: 20.46 | D13: 10.62
... A151: SKU0150 | B151: 90 | C151: 49.47 | D151: 24.62

Sheet ABC_Analysis
A1: SKU ID | B1: Category | C1: Units Sold (12M) | D1: Revenue (12M, ₹) | E1: Revenue Rank | F1: Cumulative Revenue % | G1: ABC Class | I1: ABC Summary
A2: SKU0001 | B2: Mobiles & Accessories | C2: 14554 | D2: 2.8489047e+08 | E2: =RANK(D2,$D$2:$D$151) -> 3 | F2: =SUMPRODUCT(($E$2:$E$151<=E2)*$D$2:$D$151)/SUM($D$2:$D$151) -> 0.14370111 | G2: =IF(F2<=0.8,"A",IF(F2<=0.95,"B","C")) -> A | I2: Class | J2: SKU Count | K2: % of SKUs | L2: % of Revenue
A3: SKU0002 | B3: Mobiles & Accessories | C3: 9249 | D3: 1.8373444e+08 | E3: =RANK(D3,$D$2:$D$151) -> 8 | F3: =SUMPRODUCT(($E$2:$E$151<=E3)*$D$2:$D$151)/SUM($D$2:$D$151) -> 0.30668493 | G3: =IF(F3<=0.8,"A",IF(F3<=0.95,"B","C")) -> A | I3: A | J3: =COUNTIF($G$2:$G$151,I3) -> 60 | K3: =J3/150 -> 0.4 | L3: =SUMIF($G$2:$G$151,I3,$D$2:$D$151)/SUM($D$2:$D$151) -> 0.79689345
A4: SKU0003 | B4: Mobiles & Accessories | C4: 14063 | D4: 2.0123576e+08 | E4: =RANK(D4,$D$2:$D$151) -> 6 | F4: =SUMPRODUCT(($E$2:$E$151<=E4)*$D$2:$D$151)/SUM($D$2:$D$151) -> 0.24887418 | G4: =IF(F4<=0.8,"A",IF(F4<=0.95,"B","C")) -> A | I4: B | J4: =COUNTIF($G$2:$G$151,I4) -> 44 | K4: =J4/150 -> 0.29333333 | L4: =SUMIF($G$2:$G$151,I4,$D$2:$D$151)/SUM($D$2:$D$151) -> 0.15170723
A5: SKU0004 | B5: Mobiles & Accessories | C5: 3845 | D5: 21803149 | E5: =RANK(D5,$D$2:$D$151) -> 82 | F5: =SUMPRODUCT(($E$2:$E$151<=E5)*$D$2:$D$151)/SUM($D$2:$D$151) -> 0.8857127 | G5: =IF(F5<=0.8,"A",IF(F5<=0.95,"B","C")) -> B | I5: C | J5: =COUNTIF($G$2:$G$151,I5) -> 46 | K5: =J5/150 -> 0.30666667 | L5: =SUMIF($G$2:$G$151,I5,$D$2:$D$151)/SUM($D$2:$D$151) -> 0.051399324
A6: SKU0005 | B6: Mobiles & Accessories | C6: 5756 | D6: 56929142 | E6: =RANK(D6,$D$2:$D$151) -> 33 | F6: =SUMPRODUCT(($E$2:$E$151<=E6)*$D$2:$D$151)/SUM($D$2:$D$151) -> 0.61692609 | G6: =IF(F6<=0.8,"A",IF(F6<=0.95,"B","C")) -> A
A7: SKU0006 | B7: Mobiles & Accessories | C7: 6988 | D7: 1.4663696e+08 | E7: =RANK(D7,$D$2:$D$151) -> 9 | F7: =SUMPRODUCT(($E$2:$E$151<=E7)*$D$2:$D$151)/SUM($D$2:$D$151) -> 0.32937096 | G7: =IF(F7<=0.8,"A",IF(F7<=0.95,"B","C")) -> A
A8: SKU0007 | B8: Mobiles & Accessories | C8: 13582 | D8: 78734854 | E8: =RANK(D8,$D$2:$D$151) -> 18 | F8: =SUMPRODUCT(($E$2:$E$151<=E8)*$D$2:$D$151)/SUM($D$2:$D$151) -> 0.46396007 | G8: =IF(F8<=0.8,"A",IF(F8<=0.95,"B","C")) -> A
A9: SKU0008 | B9: Mobiles & Accessories | C9: 12175 | D9: 53013237 | E9: =RANK(D9,$D$2:$D$151) -> 36 | F9: =SUMPRODUCT(($E$2:$E$151<=E9)*$D$2:$D$151)/SUM($D$2:$D$151) -> 0.64236058 | G9: =IF(F9<=0.8,"A",IF(F9<=0.95,"B","C")) -> A
A10: SKU0009 | B10: Mobiles & Accessories | C10: 4182 | D10: 60306656 | E10: =RANK(D10,$D$2:$D$151) -> 29 | F10: =SUMPRODUCT(($E$2:$E$151<=E10)*$D$2:$D$151)/SUM($D$2:$D$151) -> 0.58066439 | G10: =IF(F10<=0.8,"A",IF(F10<=0.95,"B","C")) -> A
A11: SKU0010 | B11: Mobiles & Accessories | C11: 7652 | D11: 50608645 | E11: =RANK(D11,$D$2:$D$151) -> 40 | F11: =SUMPRODUCT(($E$2:$E$151<=E11)*$D$2:$D$151)/SUM($D$2:$D$151) -> 0.67427495 | G11: =IF(F11<=0.8,"A",IF(F11<=0.95,"B","C")) -> A
A12: SKU0011 | B12: Mobiles & Accessories | C12: 5545 | D12: 59623666 | E12: =RANK(D12,$D$2:$D$151) -> 30 | F12: =SUMPRODUCT(($E$2:$E$151<=E12)*$D$2:$D$151)/SUM($D$2:$D$151) -> 0.5898887 | G12: =IF(F12<=0.8,"A",IF(F12<=0.95,"B","C")) -> A
A13: SKU0012 | B13: Mobiles & Accessories | C13: 5924 | D13: 28847984 | E13: =RANK(D13,$D$2:$D$151) -> 60 | F13: =SUMPRODUCT(($E$2:$E$151<=E13)*$D$2:$D$151)/SUM($D$2:$D$151) -> 0.79689345 | G13: =IF(F13<=0.8,"A",IF(F13<=0.95,"B","C")) -> A
A14: SKU0013 | B14: Mobiles & Accessories | C14: 5113 | D14: 49508463 | E14: =RANK(D14,$D$2:$D$151) -> 43 | F14: =SUMPRODUCT(($E$2:$E$151<=E14)*$D$2:$D$151)/SUM($D$2:$D$151) -> 0.69730535 | G14: =IF(F14<=0.8,"A",IF(F14<=0.95,"B","C")) -> A
A15: SKU0014 | B15: Mobiles & Accessories | C15: 6869 | D15: 1.2505069e+08 | E15: =RANK(D15,$D$2:$D$151) -> 10 | F15: =SUMPRODUCT(($E$2:$E$151<=E15)*$D$2:$D$151)/SUM($D$2:$D$151) -> 0.3487174 | G15: =IF(F15<=0.8,"A",IF(F15<=0.95,"B","C")) -> A
A16: SKU0015 | B16: Mobiles & Accessories | C16: 12661 | D16: 66365417 | E16: =RANK(D16,$D$2:$D$151) -> 24 | F16: =SUMPRODUCT(($E$2:$E$151<=E16)*$D$2:$D$151)/SUM($D$2:$D$151) -> 0.53142653 | G16: =IF(F16<=0.8,"A",IF(F16<=0.95,"B","C")) -> A
A17: SKU0016 | B17: Mobiles & Accessories | C17: 3968 | D17: 12006176 | E17: =RANK(D17,$D$2:$D$151) -> 109 | F17: =SUMPRODUCT(($E$2:$E$151<=E17)*$D$2:$D$151)/SUM($D$2:$D$151) -> 0.95869129 | G17: =IF(F17<=0.8,"A",IF(F17<=0.95,"B","C")) -> C
... A151: SKU0150 | B151: Grocery & Essentials | C151: 13400 | D151: 2170264 | E151: =RANK(D151,$D$2:$D$151) -> 149 | F151: =SUMPRODUCT(($E$2:$E$151<=E151)*$D$2:$D$151)/SUM($D$2:$D$151) -> 0.99989784 | G151: =IF(F151<=0.8,"A",IF(F151<=0.95,"B","C")) -> C

Sheet Reorder_Point_Calc
A1: SKU ID | B1: ABC Class | C1: Avg Daily Demand | D1: Std Dev Demand | E1: Lead Time (days) | F1: Service Level Z | G1: Safety Stock (units) | H1: Reorder Point (units) | I1: Net On-Hand (units) | J1: Action | L1: Formulas: Safety Stock = Z × σ(demand) × √(Lead Time) | Reorder Point = (Avg Demand × Lead Time) + Safety Stock
A2: =SKU_Master!A2 -> SKU0001 | B2: =ABC_Analysis!G2 -> A | C2: =Demand_Stats!C2 -> 52.63 | D2: =Demand_Stats!D2 -> 24.39 | E2: =SKU_Master!F2 -> 5 | F2: =IF(B2="A",2.05,IF(B2="B",1.65,1.28)) -> 2.05 | G2: =ROUND(F2*D2*SQRT(E2),1) -> 111.8 | H2: =ROUND((C2*E2)+G2,1) -> 375 | I2: 0 | J2: =IF(I2<=H2,"REORDER NOW","OK") -> REORDER NOW | L2: Net On-Hand: Source = current inventory snapshot (SQL, inventory_snapshot table), network-wide sum across assigned FCs.
A3: =SKU_Master!A3 -> SKU0002 | B3: =ABC_Analysis!G3 -> A | C3: =Demand_Stats!C3 -> 33.32 | D3: =Demand_Stats!D3 -> 16.7 | E3: =SKU_Master!F3 -> 4 | F3: =IF(B3="A",2.05,IF(B3="B",1.65,1.28)) -> 2.05 | G3: =ROUND(F3*D3*SQRT(E3),1) -> 68.5 | H3: =ROUND((C3*E3)+G3,1) -> 201.8 | I3: 0 | J3: =IF(I3<=H3,"REORDER NOW","OK") -> REORDER NOW
A4: =SKU_Master!A4 -> SKU0003 | B4: =ABC_Analysis!G4 -> A | C4: =Demand_Stats!C4 -> 53.84 | D4: =Demand_Stats!D4 -> 27 | E4: =SKU_Master!F4 -> 5 | F4: =IF(B4="A",2.05,IF(B4="B",1.65,1.28)) -> 2.05 | G4: =ROUND(F4*D4*SQRT(E4),1) -> 123.8 | H4: =ROUND((C4*E4)+G4,1) -> 393 | I4: 1 | J4: =IF(I4<=H4,"REORDER NOW","OK") -> REORDER NOW
A5: =SKU_Master!A5 -> SKU0004 | B5: =ABC_Analysis!G5 -> B | C5: =Demand_Stats!C5 -> 14.69 | D5: =Demand_Stats!D5 -> 8.05 | E5: =SKU_Master!F5 -> 3 | F5: =IF(B5="A",2.05,IF(B5="B",1.65,1.28)) -> 1.65 | G5: =ROUND(F5*D5*SQRT(E5),1) -> 23 | H5: =ROUND((C5*E5)+G5,1) -> 67.1 | I5: 0 | J5: =IF(I5<=H5,"REORDER NOW","OK") -> REORDER NOW
A6: =SKU_Master!A6 -> SKU0005 | B6: =ABC_Analysis!G6 -> A | C6: =Demand_Stats!C6 -> 21.77 | D6: =Demand_Stats!D6 -> 10.92 | E6: =SKU_Master!F6 -> 2 | F6: =IF(B6="A",2.05,IF(B6="B",1.65,1.28)) -> 2.05 | G6: =ROUND(F6*D6*SQRT(E6),1) -> 31.7 | H6: =ROUND((C6*E6)+G6,1) -> 75.2 | I6: 95 | J6: =IF(I6<=H6,"REORDER NOW","OK") -> OK
A7: =SKU_Master!A7 -> SKU0006 | B7: =ABC_Analysis!G7 -> A | C7: =Demand_Stats!C7 -> 27.13 | D7: =Demand_Stats!D7 -> 14.8 | E7: =SKU_Master!F7 -> 7 | F7: =IF(B7="A",2.05,IF(B7="B",1.65,1.28)) -> 2.05 | G7: =ROUND(F7*D7*SQRT(E7),1) -> 80.3 | H7: =ROUND((C7*E7)+G7,1) -> 270.2 | I7: 18 | J7: =IF(I7<=H7,"REORDER NOW","OK") -> REORDER NOW
A8: =SKU_Master!A8 -> SKU0007 | B8: =ABC_Analysis!G8 -> A | C8: =Demand_Stats!C8 -> 49.72 | D8: =Demand_Stats!D8 -> 23.57 | E8: =SKU_Master!F8 -> 5 | F8: =IF(B8="A",2.05,IF(B8="B",1.65,1.28)) -> 2.05 | G8: =ROUND(F8*D8*SQRT(E8),1) -> 108 | H8: =ROUND((C8*E8)+G8,1) -> 356.6 | I8: 0 | J8: =IF(I8<=H8,"REORDER NOW","OK") -> REORDER NOW
A9: =SKU_Master!A9 -> SKU0008 | B9: =ABC_Analysis!G9 -> A | C9: =Demand_Stats!C9 -> 44.82 | D9: =Demand_Stats!D9 -> 22.42 | E9: =SKU_Master!F9 -> 4 | F9: =IF(B9="A",2.05,IF(B9="B",1.65,1.28)) -> 2.05 | G9: =ROUND(F9*D9*SQRT(E9),1) -> 91.9 | H9: =ROUND((C9*E9)+G9,1) -> 271.2 | I9: 0 | J9: =IF(I9<=H9,"REORDER NOW","OK") -> REORDER NOW
A10: =SKU_Master!A10 -> SKU0009 | B10: =ABC_Analysis!G10 -> A | C10: =Demand_Stats!C10 -> 13.59 | D10: =Demand_Stats!D10 -> 7.63 | E10: =SKU_Master!F10 -> 4 | F10: =IF(B10="A",2.05,IF(B10="B",1.65,1.28)) -> 2.05 | G10: =ROUND(F10*D10*SQRT(E10),1) -> 31.3 | H10: =ROUND((C10*E10)+G10,1) -> 85.7 | I10: 21 | J10: =IF(I10<=H10,"REORDER NOW","OK") -> REORDER NOW
A11: =SKU_Master!A11 -> SKU0010 | B11: =ABC_Analysis!G11 -> A | C11: =Demand_Stats!C11 -> 26.71 | D11: =Demand_Stats!D11 -> 13.2 | E11: =SKU_Master!F11 -> 3 | F11: =IF(B11="A",2.05,IF(B11="B",1.65,1.28)) -> 2.05 | G11: =ROUND(F11*D11*SQRT(E11),1) -> 46.9 | H11: =ROUND((C11*E11)+G11,1) -> 127 | I11: 0 | J11: =IF(I11<=H11,"REORDER NOW","OK") -> REORDER NOW
A12: =SKU_Master!A12 -> SKU0011 | B12: =ABC_Analysis!G12 -> A | C12: =Demand_Stats!C12 -> 20.89 | D12: =Demand_Stats!D12 -> 11.88 | E12: =SKU_Master!F12 -> 2 | F12: =IF(B12="A",2.05,IF(B12="B",1.65,1.28)) -> 2.05 | G12: =ROUND(F12*D12*SQRT(E12),1) -> 34.4 | H12: =ROUND((C12*E12)+G12,1) -> 76.2 | I12: 84 | J12: =IF(I12<=H12,"REORDER NOW","OK") -> OK
A13: =SKU_Master!A13 -> SKU0012 | B13: =ABC_Analysis!G13 -> A | C13: =Demand_Stats!C13 -> 20.46 | D13: =Demand_Stats!D13 -> 10.62 | E13: =SKU_Master!F13 -> 5 | F13: =IF(B13="A",2.05,IF(B13="B",1.65,1.28)) -> 2.05 | G13: =ROUND(F13*D13*SQRT(E13),1) -> 48.7 | H13: =ROUND((C13*E13)+G13,1) -> 151 | I13: 28 | J13: =IF(I13<=H13,"REORDER NOW","OK") -> REORDER NOW
A14: =SKU_Master!A14 -> SKU0013 | B14: =ABC_Analysis!G14 -> A | C14: =Demand_Stats!C14 -> 18.09 | D14: =Demand_Stats!D14 -> 10.04 | E14: =SKU_Master!F14 -> 14 | F14: =IF(B14="A",2.05,IF(B14="B",1.65,1.28)) -> 2.05 | G14: =ROUND(F14*D14*SQRT(E14),1) -> 77 | H14: =ROUND((C14*E14)+G14,1) -> 330.3 | I14: 58 | J14: =IF(I14<=H14,"REORDER NOW","OK") -> REORDER NOW
... A151: =SKU_Master!A151 -> SKU0150 | B151: =ABC_Analysis!G151 -> C | C151: =Demand_Stats!C151 -> 49.47 | D151: =Demand_Stats!D151 -> 24.62 | E151: =SKU_Master!F151 -> 3 | F151: =IF(B151="A",2.05,IF(B151="B",1.65,1.28)) -> 1.28 | G151: =ROUND(F151*D151*SQRT(E151),1) -> 54.6 | H151: =ROUND((C151*E151)+G151,1) -> 203 | I151: 0 | J151: =IF(I151<=H151,"REORDER NOW","OK") -> REORDER NOW

Sheet Fill_Rate_Impact
B2: Before vs After: Reorder Policy Impact (Last 12 Weeks)
B3: AFTER = simulated result of replacing the naive weekly-review policy with the ABC-tiered, forecast-driven reorder-point policy from this workbook.
B5: Fill Rate — BEFORE (naive weekly-review policy) | D5: 0.8318
B6: Fill Rate — AFTER (ABC-tiered, forecast-driven policy) | D6: 0.9969
B7: Improvement (percentage points) | D7: 16.5
B8: Total Demand, units (12-wk window) | D8: 509001
B9: Lost Sales — BEFORE, units | D9: 85604
B10: Lost Sales — AFTER (estimated), units | D10: 1595

Sheet Forecast_Model
B2: Demand Forecasting Model — Benchmark (WMAPE %, lower = better)
B4: Model | C4: WMAPE %
B5: Naive (last week) | C5: 28.218762
B6: Moving Average (4wk) | C6: 20.842027
B7: Random Forest | C7: 13.981581
B8: Gradient Boosting | C8: 14.298394
B10: Winning model: Random Forest Regressor (engineered lag + rolling-window + calendar features, weekly SKU-level demand).
B11: Trained/evaluated in Python (scikit-learn); see 03_forecasting_model.py. Time-based 8-week holdout, no leakage (all features causal).
B14: Next-Week Demand Forecast (sample, top 15 by forecast volume)
B15: SKU ID | C15: Category | D15: Forecast Week | E15: Forecast Demand (units)
B16: SKU0143 | C16: Grocery & Essentials | D16: 2026-01-06 | E16: 908.1
B17: SKU0141 | C17: Grocery & Essentials | D17: 2026-01-06 | E17: 906.6
B18: SKU0137 | C18: Grocery & Essentials | D18: 2026-01-06 | E18: 903.1
B19: SKU0139 | C19: Grocery & Essentials | D19: 2026-01-06 | E19: 882.2
B20: SKU0148 | C20: Grocery & Essentials | D20: 2026-01-06 | E20: 807.9
B21: SKU0140 | C21: Grocery & Essentials | D21: 2026-01-06 | E21: 637
B22: SKU0142 | C22: Grocery & Essentials | D22: 2026-01-06 | E22: 629.3
B23: SKU0135 | C23: Grocery & Essentials | D23: 2026-01-06 | E23: 621.8
B24: SKU0051 | C24: Fashion & Apparel | D24: 2026-01-06 | E24: 610.1
B25: SKU0138 | C25: Grocery & Essentials | D25: 2026-01-06 | E25: 608.4
B26: SKU0147 | C26: Grocery & Essentials | D26: 2026-01-06 | E26: 607.6
B27: SKU0066 | C27: Fashion & Apparel | D27: 2026-01-06 | E27: 607.3
... B30: SKU0063 | C30: Fashion & Apparel | D30: 2026-01-06 | E30: 604.1

Sheet Reorder_Alerts
B1: Automated Reorder Alerts (AI Automation Layer — prioritized, urgency-ranked)
A3: SKU ID | B3: SKU Name | C3: Category | D3: ABC Class | E3: On Hand | F3: Days of Cover | G3: Lead Time (days) | H3: Forecast Demand (next wk) | I3: Urgency | J3: Suggested Order Qty
A4: SKU0001 | B4: Mobiles Item 001 | C4: Mobiles & Accessories | D4: A | E4: 0 | F4: 0 | G4: 5 | H4: 491.4 | I4: CRITICAL | J4: 1446
A5: SKU0002 | B5: Mobiles Item 002 | C5: Mobiles & Accessories | D5: A | E5: 0 | F5: 0 | G5: 4 | H5: 269.4 | I5: CRITICAL | J5: 761
A6: SKU0003 | B6: Mobiles Item 003 | C6: Mobiles & Accessories | D6: A | E6: 1 | F6: 0 | G6: 5 | H6: 493.3 | I6: CRITICAL | J6: 1462
A7: SKU0006 | B7: Mobiles Item 006 | C7: Mobiles & Accessories | D7: A | E7: 18 | F7: 0.7 | G7: 7 | H7: 225.4 | I7: CRITICAL | J7: 738
A8: SKU0007 | B8: Mobiles Item 007 | C8: Mobiles & Accessories | D8: A | E8: 0 | F8: 0 | G8: 5 | H8: 466.3 | I8: CRITICAL | J8: 1374
A9: SKU0008 | B9: Mobiles Item 008 | C9: Mobiles & Accessories | D9: A | E9: 0 | F9: 0 | G9: 4 | H9: 421.2 | I9: CRITICAL | J9: 1175
A10: SKU0009 | B10: Mobiles Item 009 | C10: Mobiles & Accessories | D10: A | E10: 21 | F10: 1.5 | G10: 4 | H10: 96.4 | I10: CRITICAL | J10: 258
A11: SKU0010 | B11: Mobiles Item 010 | C11: Mobiles & Accessories | D11: A | E11: 0 | F11: 0 | G11: 3 | H11: 214.9 | I11: CRITICAL | J11: 569
A12: SKU0012 | B12: Mobiles Item 012 | C12: Mobiles & Accessories | D12: A | E12: 28 | F12: 1.4 | G12: 5 | H12: 172.6 | I12: CRITICAL | J12: 489
A13: SKU0013 | B13: Mobiles Item 013 | C13: Mobiles & Accessories | D13: A | E13: 58 | F13: 3.2 | G13: 14 | H13: 163.7 | I13: CRITICAL | J13: 674
A14: SKU0015 | B14: Mobiles Item 015 | C14: Mobiles & Accessories | D14: A | E14: 42 | F14: 0.9 | G14: 7 | H14: 461.6 | I14: CRITICAL | J14: 1480
A15: SKU0017 | B15: Mobiles Item 017 | C15: Mobiles & Accessories | D15: A | E15: 0 | F15: 0 | G15: 3 | H15: 342.4 | I15: CRITICAL | J15: 906
... A126: SKU0090 | B126: Home Item 015 | C126: Home & Kitchen | D126: B | E126: 86 | F126: 5.1 | G126: 5 | H126: 141.3 | I126: MEDIUM | J126: 331
